<InformeFacturacion><DiaSemana><dia_de_la_semana>domingo</dia_de_la_semana><total_facturado>4324.00</total_facturado></DiaSemana><DiaSemana><dia_de_la_semana>lunes</dia_de_la_semana><total_facturado>262.00</total_facturado></DiaSemana><DiaSemana><dia_de_la_semana>martes</dia_de_la_semana><total_facturado>168.00</total_facturado></DiaSemana><DiaSemana><dia_de_la_semana>miércoles</dia_de_la_semana><total_facturado>143.00</total_facturado></DiaSemana><DiaSemana><dia_de_la_semana>jueves</dia_de_la_semana><total_facturado>75.00</total_facturado></DiaSemana><DiaSemana><dia_de_la_semana>viernes</dia_de_la_semana><total_facturado>200.00</total_facturado></DiaSemana><DiaSemana><dia_de_la_semana>sábado</dia_de_la_semana><total_facturado>66.00</total_facturado></DiaSemana></InformeFacturacion>